jinja2_webpack-0.2.0.dist-info/METADATA
jinja2_webpack-0.2.0.dist-info/WHEEL
jinja2_webpack-0.2.0.dist-info/DESCRIPTION.rst
jinja2_webpack-0.2.0.dist-info/metadata.json
jinja2_webpack-0.2.0.dist-info/entry_points.txt
jinja2_webpack-0.2.0.dist-info/RECORD
jinja2_webpack-0.2.0.dist-info/top_level.txt
jinja2_webpack/renderer.py
jinja2_webpack/scan.py
jinja2_webpack/__init__.py
jinja2_webpack/filter.py
jinja2_webpack/utils/__init__.py
jinja2_webpack/utils/load_json.py
jinja2_webpack/utils/normalize_path.py
